{
  "tile": 16,
  "width": 608,
  "height": 384,
  "grid": {
    "w": 38,
    "h": 24
  },
  "source": "kenney-semantic-v2",
  "playbook": "semantic_playbook.json",
  "packs": [
    "Tiny Town (Kenney CC0)",
    "RPG Urban Pack (Kenney CC0) \u2014 sidewalk + brick only",
    "Tiny Dungeon (Kenney CC0) \u2014 floors/furniture"
  ],
  "credit": "Assets by Kenney (www.kenney.nl) CC0. Semantic composition State of VD.",
  "layers": {
    "ground": "ground.png",
    "roofs": "roofs.png",
    "interiors": "interiors.png"
  },
  "ids": {
    "grass": [
      0,
      1,
      2
    ],
    "path": [
      12,
      13,
      14,
      24,
      36,
      37,
      38
    ],
    "water": [
      48,
      49
    ],
    "road": [
      8,
      9,
      10,
      11,
      12,
      13,
      14,
      15
    ],
    "brick": [
      16,
      17,
      18,
      19,
      20,
      21,
      22
    ],
    "roof": [
      43,
      44,
      45,
      46,
      47,
      48,
      49
    ],
    "door": [
      54,
      55,
      56,
      57
    ],
    "floor": [
      0,
      1,
      2,
      3,
      16,
      17,
      18,
      19,
      20,
      21,
      22,
      23
    ]
  }
}